grins/__init__.py
grins/boolise.py
grins/gen_diffrax_ode.py
grins/gen_params.py
grins/ising_bool.py
grins/logical_bool.py
grins/racipe.py
grins/racipe_run.py
grins/reg_funcs.py
grins/test_diffrax.py
grins-0.1.2.dist-info/LICENSE
grins-0.1.2.dist-info/METADATA
grins-0.1.2.dist-info/WHEEL
grins-0.1.2.dist-info/entry_points.txt
grins-0.1.2.dist-info/RECORD
