Metadata-Version: 2.3
Name: grins
Version: 0.1.2
Summary: Gene Regulatory Interaction Network Simulator - GRiNS
License: GPL-3.0-or-later
Author: MoltenEcdysone09
Author-email: pradyumnah@iisc.ac.in
Requires-Python: >=3.12,<4.0
Classifier: Intended Audience :: Science/Research
Classifier: License :: OSI Approved :: GNU General Public License v3 or later (GPLv3+)
Classifier: Operating System :: OS Independent
Classifier: Programming Language :: Python :: 3
Classifier: Programming Language :: Python :: 3.12
Classifier: Programming Language :: Python :: 3.13
Classifier: Topic :: Scientific/Engineering
Provides-Extra: cuda12
Requires-Dist: diffrax (>=0.6.2,<0.7.0)
Requires-Dist: jax[cuda12] (>=0.5.3) ; extra == "cuda12"
Requires-Dist: networkx (>=3.4.2,<4.0.0)
Requires-Dist: numpy (>=2.2.3,<3.0.0)
Requires-Dist: pandas (>=2.2.3,<3.0.0)
Requires-Dist: pyarrow (>=19.0.1,<20.0.0)
Requires-Dist: scipy (>=1.15.2,<2.0.0)
Project-URL: Bug Tracker, https://github.com/MoltenEcdysone09/GRiNS/issues
Project-URL: Documentation, https://moltenecdysone09.github.io/GRiNS/
Project-URL: Homepage, https://github.com/MoltenEcdysone09/GRiNS
Project-URL: Repository, https://github.com/MoltenEcdysone09/GRiNS
